music_cue/__init__.py
music_cue/base_logger.py
music_cue/command_line.py
music_cue/data_handler.py
music_cue/gui.py
music_cue/utils.py
music_cue-0.1.6.dist-info/licenses/LICENCE
music_cue-0.1.6.dist-info/METADATA
music_cue-0.1.6.dist-info/WHEEL
music_cue-0.1.6.dist-info/entry_points.txt
music_cue-0.1.6.dist-info/top_level.txt
music_cue-0.1.6.dist-info/RECORD
