Metadata-Version: 2.4
Name: music-cue
Version: 0.1.6
Summary: A data entry application
Home-page: https://github.com/hans-vvv/Music-Cue
Author: Hans Verkerk
Author-email: verkerk.hans@gmail.com
License: MIT
License-File: LICENCE
Requires-Dist: openpyxl
Requires-Dist: ttkbootstrap
Dynamic: author
Dynamic: author-email
Dynamic: home-page
Dynamic: license
Dynamic: license-file
Dynamic: requires-dist
Dynamic: summary
